aiida_pythonjob/__init__.py
aiida_pythonjob/config.py
aiida_pythonjob/decorator.py
aiida_pythonjob/launch.py
aiida_pythonjob/utils.py
aiida_pythonjob/calculations/__init__.py
aiida_pythonjob/calculations/common.py
aiida_pythonjob/calculations/pyfunction.py
aiida_pythonjob/calculations/pythonjob.py
aiida_pythonjob/calculations/tasks.py
aiida_pythonjob/calculations/utils.py
aiida_pythonjob/data/__init__.py
aiida_pythonjob/data/atoms.py
aiida_pythonjob/data/common_data.py
aiida_pythonjob/data/deserializer.py
aiida_pythonjob/data/jsonable_data.py
aiida_pythonjob/data/pickled_data.py
aiida_pythonjob/data/serializer.py
aiida_pythonjob/data/utils.py
aiida_pythonjob/parsers/__init__.py
aiida_pythonjob/parsers/pythonjob.py
aiida_pythonjob/parsers/utils.py
aiida_pythonjob-0.4.7.dist-info/licenses/LICENSE
aiida_pythonjob-0.4.7.dist-info/METADATA
aiida_pythonjob-0.4.7.dist-info/WHEEL
aiida_pythonjob-0.4.7.dist-info/entry_points.txt
aiida_pythonjob-0.4.7.dist-info/top_level.txt
aiida_pythonjob-0.4.7.dist-info/RECORD
