Metadata-Version: 2.4
Name: aiida-pythonjob
Version: 0.4.7
Summary: Run Python functions on a remote computer.
Author-email: Xing Wang <xingwang1991@gmail.com>
License: MIT License
Project-URL: Source, https://github.com/aiidateam/aiida-pythonjob
Keywords: aiida,plugin
Classifier: Programming Language :: Python
Classifier: Intended Audience :: Science/Research
Classifier: License :: OSI Approved :: MIT License
Classifier: Natural Language :: English
Classifier: Development Status :: 3 - Alpha
Classifier: Framework :: AiiDA
Requires-Python: >=3.9
License-File: LICENSE
Requires-Dist: aiida-core<3,>=2.7.1
Requires-Dist: ase
Requires-Dist: node-graph~=0.4.0
Provides-Extra: test
Requires-Dist: pgtest>=1.3.1,~=1.3; extra == "test"
Requires-Dist: coverage~=7.0; extra == "test"
Requires-Dist: pytest~=7.0; extra == "test"
Requires-Dist: pytest-cov~=4.1; extra == "test"
Requires-Dist: ipdb; extra == "test"
Provides-Extra: pre-commit
Requires-Dist: pre-commit~=3.5; extra == "pre-commit"
Provides-Extra: docs
Requires-Dist: sphinx_rtd_theme; extra == "docs"
Requires-Dist: sphinx; extra == "docs"
Requires-Dist: sphinxcontrib-contentui; extra == "docs"
Requires-Dist: sphinxcontrib-details-directive; extra == "docs"
Requires-Dist: sphinx-gallery; extra == "docs"
Requires-Dist: furo; extra == "docs"
Requires-Dist: markupsafe<2.1; extra == "docs"
Requires-Dist: nbsphinx; extra == "docs"
Dynamic: license-file
